colcon_common_extensions/__init__.py
colcon_common_extensions-0.2.0.dist-info/DESCRIPTION.rst
colcon_common_extensions-0.2.0.dist-info/METADATA
colcon_common_extensions-0.2.0.dist-info/RECORD
colcon_common_extensions-0.2.0.dist-info/WHEEL
colcon_common_extensions-0.2.0.dist-info/metadata.json
colcon_common_extensions-0.2.0.dist-info/top_level.txt
colcon_common_extensions-0.2.0.dist-info/zip-safe
